mpkz-0.1.0.dist-info/METADATA
mpkz-0.1.0.dist-info/WHEEL
mpkz/__init__.py
mpkz/__init__.pyi
mpkz/py.typed
mpkz/mpkz.pypy39-pp73-x86_64-linux-gnu.so
mpkz-0.1.0.dist-info/RECORD
